charbychar/__init__.py
charbychar/charbychar.py
charbychar-0.0.1.dist-info/LICENSE
charbychar-0.0.1.dist-info/METADATA
charbychar-0.0.1.dist-info/WHEEL
charbychar-0.0.1.dist-info/top_level.txt
charbychar-0.0.1.dist-info/RECORD
