Metadata-Version: 2.1
Name: charbychar
Version: 0.0.1
Summary: Write strings letter-by-letter
Home-page: https://github.com/j0of/charbychar
Author: Joffrey Estrella (j0of)
Author-email: joof.leturtle@gmail.com
Classifier: Programming Language :: Python :: 3.11
Classifier: License :: OSI Approved :: MIT License
Classifier: Operating System :: OS Independent
Requires-Python: >=3.7
License-File: LICENSE
